{
    "display": {
        "icon": {
            "item": "kubejs:quest_aether"
        },
        "title": "Find a Bronze Dungeon",
        "description": "Bronze Dungeons are hidden underground but they have an open exit.\n\nREWARDS:\n\u00a7f\u00a7o- 2 \u00a77\ud83e\ude99",
        "frame": "task",
        "show_toast": false,
        "announce_to_chat": true,
        "hidden": false
    },
    "parent": "aaaa_zp4adv:place_aether_altar",
    "criteria": {
        "thecriteria": {
            "trigger": "minecraft:impossible"
        }
    },
    "requirements": [
        [
            "thecriteria"
        ]
    ],
    "rewards": {
        "experience": 120
    },
    "sends_telemetry_event": false
}