{
    "display": {
        "icon": {
            "item": "kubejs:quest_aether"
        },
        "title": "Slay 10 Valkyries",
        "description": "The Valkyries are submissive to their queen. You need their medals to trade with the Queen.\n\nREWARDS:\n\u00a7f\u00a7o- 58 \u00a77\ud83e\ude99\n\u00a7f\u00a7o- 3 \u00a76\ud83e\ude99",
        "frame": "task",
        "show_toast": false,
        "announce_to_chat": true,
        "hidden": false
    },
    "parent": "aaaa_zp4adv:locate_aether_silver_dungeon",
    "criteria": {
        "thecriteria": {
            "trigger": "minecraft:impossible"
        }
    },
    "requirements": [
        [
            "thecriteria"
        ]
    ],
    "rewards": {
        "experience": 40000
    },
    "sends_telemetry_event": false
}