{
        "loading_priority": 111,
	"powers": [
                "medievalorigins:plague_victim/foul_aura",
		"medievalorigins:plague_victim/plague_immunity",
                "medievalorigins:plague_victim/risk_of_transmission",
                "medievalorigins:plague_victim/sensitive_skin",
                "medievalorigins:plague_victim/skin_and_bones",
                "origins_survive:illness_resistance"
	],
        "icon": {
		"item": "minecraft:ink_sac",
		"tag": "{CustomModelData:368}"
},
	"impact": 3,
        "order": 1
}
